{
	"categories": [
		{
			"name": "blocks",
			"blocks": [
				{
					"name": "craft",
					"directory": "src/lib/components/blocks/craft",
					"category": "blocks",
					"tests": false,
					"subdirectory": true,
					"list": true,
					"files": [
						"Article.svelte",
						"Box.svelte",
						"Container.svelte",
						"craft.ts",
						"index.ts",
						"Layout.svelte",
						"Main.svelte",
						"Prose.svelte",
						"Section.svelte"
					],
					"localDependencies": [],
					"dependencies": [],
					"devDependencies": [
						"clsx@^2.1.1",
						"tailwind-merge@^3.0.2"
					],
					"_imports_": {}
				}
			]
		}
	]
}